Workbook

Sheet Dashboard
A1: INVESTMENT ANALYSIS DASHBOARD — PLTR vs NOW | June 2026
A3: PALANTIR TECHNOLOGIES (PLTR) | E3: SERVICENOW (NOW)
A4: Metric | B4: Value | C4: Notes/Source | E4: Metric | F4: Value | G4: Notes/Source
A5: Company | B5: Palantir Technologies | E5: Company | F5: ServiceNow, Inc.
A6: Ticker | B6: PLTR | E6: Ticker | F6: NOW
A7: Current Price ($) | B7: =PLTR_Model!$B$51 -> 141.51 | E7: Current Price ($) | F7: =NOW_Model!$B$53 -> 119.29
A8: Market Cap ($B, approx.) | B8: =PLTR_Model!$B$51*PLTR_Model!$B$50/1000 -> 363.82221 | C8: Price x Diluted Shares | E8: Market Cap ($B, approx.) | F8: =NOW_Model!$B$53*NOW_Model!$B$52/1000 -> 124.0616 | G8: Price x Diluted Shares
A9: FY2026 Revenue ($M, Base) | B9: =PLTR_Model!B36 -> 7655.67 | C9: Base scenario | E9: FY2026 Revenue ($M, Base) | F9: =NOW_Model!B39 -> 16100 | G9: Base scenario
A10: FY2026 Rev Growth (Base) | B10: =PLTR_Model!B35 -> 0.71 | C10: Base scenario | E10: FY2026 Rev Growth (Base) | F10: =NOW_Model!B38 -> 0.22 | G10: Base scenario
A11: Gross Margin (Q1 2026) | B11: 0.87 | C11: Q1 2026 actual | E11: Gross Margin (Q1 2026) | F11: 0.795 | G11: Non-GAAP Q1 2026
A12: Adj. Op Margin (Q1 2026) | B12: 0.6 | C12: Adj./Non-GAAP | E12: Non-GAAP Op Margin (Q1 '26) | F12: 0.32 | G12: Non-GAAP Q1 2026
A13: FCF Margin (Q1 2026) | B13: 0.57 | C13: Adj. FCF margin | E13: FCF Margin (Q1 2026) | F13: 0.44 | G13: Non-GAAP
A14: Rule of 40 (Q1 2026) | B14: 145 | C14: 85%+60%=145 | E14: Rule of 40 (Q1 2026) | F14: 54 | G14: 22%+32%=54
A15: EV/Sales FY2026 (est.) | B15: 46.5 | C15: Analyst est. | E15: EV/Sales FY2026 (est.) | F15: 7.5 | G15: Analyst est.
A16: EV/FCF FY2026 (est.) | B16: 82.7 | C16: Analyst est. | E16: EV/FCF FY2026 (est.) | F16: 21.3 | G16: Analyst est.
A17: DCF Intrinsic — Bull ($) | B17: =PLTR_Model!$B$64 -> 71.383872 | C17: Linked from model | E17: DCF Intrinsic — Bull ($) | F17: =NOW_Model!$B$66 -> 178.71138 | G17: Linked from model
A18: DCF Intrinsic — Base ($) | B18: =PLTR_Model!$B$78 -> 40.157794 | C18: Linked from model | E18: DCF Intrinsic — Base ($) | F18: =NOW_Model!$B$80 -> 126.26237 | G18: Linked from model
A19: DCF Intrinsic — Bear ($) | B19: =PLTR_Model!$B$92 -> 20.504545 | C19: Linked from model | E19: DCF Intrinsic — Bear ($) | F19: =NOW_Model!$B$94 -> 81.037468 | G19: Linked from model
A20: Price vs DCF Base (%) | B20: =(PLTR_Model!$B$51-PLTR_Model!$B$78)/PLTR_Model!$B$78 -> 2.523849 | C20: (-) = premium | E20: Price vs DCF Base (%) | F20: =(NOW_Model!$B$53-NOW_Model!$B$80)/NOW_Model!$B$80 -> -0.055221248 | G20: (-) = premium
A21: IV (%) | B21: 0.6879 | C21: June 2026 | E21: IV (%, estimate) | G21: Verify live
A22: IV Rank | B22: 46.73 | C22: June 2026 | E22: IV Rank (estimate) | G22: Verify live
A23: 200-day SMA ($) | B23: 162 | C23: June 2026 | E23: 52-wk High ($) | F23: 211.48 | G23: 52-wk range
A24: 52-Week High (est., $) | C24: ~$170 est. | E24: 52-wk Low ($) | F24: 81.24 | G24: 52-wk range
A25: 52-Week Low (est., $) | C25: ~$70 est. | E25: 200-day SMA ($) | G25: Verify live
A28: COLOR CODING LEGEND
A29: Blue text | B29: Hardcoded inputs — user-editable assumptions and market data
A30: Black text | B30: Formulas and calculated outputs
A31: Green text | B31: Cross-sheet links pulling data from PLTR_Model or NOW_Model
A32: Gold background | B32: Key output cells: DCF intrinsic values, Rule of 40 scores

Sheet PLTR_Model
A1: PALANTIR TECHNOLOGIES (PLTR) — Investment Analysis Model
A2: SECTION A — HISTORICAL DATA (FY2024–Q1 2026)
A3: Metric | B3: FY2024 | C3: FY2025 | D3: Q1 2025 | E3: Q2 2025 | F3: Q3 2025 | G3: Q4 2025 | H3: Q1 2026
A4: Revenue ($M) | B4: 2865 | C4: 4477 | D4: 883.9 | E4: 1004 | F4: 1181 | G4: 1408 | H4: 1632.6
A5: YoY Revenue Growth | C5: 0.563 | H5: 0.869
A6: Gross Margin | H6: 0.87
A7: Adj. Operating Margin | B7: 0.36 | C7: 0.5 | H7: 0.6
A8: GAAP Operating Margin | H8: 0.46
A9: Adj. FCF Margin | H9: 0.57
A10: Adj. FCF ($M) | C10: 2239
A11: Adj. EBITDA ($M) | H11: 990.3
A12: Adj. EBITDA Margin | H12: 0.61
A13: SBC ($M) | H13: 201.6
A14: SBC % of Revenue | H14: 0.123
A16: Revenue Segment Detail (Q1 2026)
A17: Metric | B17: Q1 2026 ($M) | C17: YoY Growth
A18: US Revenue ($M) | B18: 1282 | C18: 1.04
A19: US Commercial Revenue ($M) | B19: 595 | C19: 1.33
A20: US Government Revenue ($M) | B20: 687 | C20: 0.84
A21: International Revenue ($M) | B21: 351
A22: Total Customers (TTM) | B22: 1007
A25: SECTION B — REVENUE & FCF PROJECTIONS (FY2026–FY2030)
A26: FY2025 Revenue ($M) [Base year for projections] | B26: 4477
A27: Year | B27: FY2026 | C27: FY2027 | D27: FY2028 | E27: FY2029 | F27: FY2030
A28: Bull Scenario
A29: Bull Rev Growth Assumption | B29: 0.71 | C29: 0.6 | D29: 0.5 | E29: 0.4 | F29: 0.3
A30: Bull Revenue ($M) | B30: =$B$26*(1+B29) -> 7655.67 | C30: =B30*(1+C29) -> 12249.072 | D30: =C30*(1+D29) -> 18373.608 | E30: =D30*(1+E29) -> 25723.051 | F30: =E30*(1+F29) -> 33439.967
A31: Bull FCF Margin Assumption | B31: 0.58 | C31: 0.6 | D31: 0.62 | E31: 0.62 | F31: 0.62
A32: Bull FCF ($M) | B32: =B30*B31 -> 4440.2886 | C32: =C30*C31 -> 7349.4432 | D32: =D30*D31 -> 11391.637 | E32: =E30*E31 -> 15948.292 | F32: =F30*F31 -> 20732.779
A34: Base Scenario
A35: Base Rev Growth Assumption | B35: 0.71 | C35: 0.5 | D35: 0.35 | E35: 0.25 | F35: 0.18
A36: Base Revenue ($M) | B36: =$B$26*(1+B35) -> 7655.67 | C36: =B36*(1+C35) -> 11483.505 | D36: =C36*(1+D35) -> 15502.732 | E36: =D36*(1+E35) -> 19378.415 | F36: =E36*(1+F35) -> 22866.529
A37: Base FCF Margin Assumption | B37: 0.56 | C37: 0.56 | D37: 0.55 | E37: 0.54 | F37: 0.52
A38: Base FCF ($M) | B38: =B36*B37 -> 4287.1752 | C38: =C36*C37 -> 6430.7628 | D38: =D36*D37 -> 8526.5025 | E38: =E36*E37 -> 10464.344 | F38: =F36*F37 -> 11890.595
A40: Bear Scenario
A41: Bear Rev Growth Assumption | B41: 0.71 | C41: 0.35 | D41: 0.2 | E41: 0.15 | F41: 0.1
A42: Bear Revenue ($M) | B42: =$B$26*(1+B41) -> 7655.67 | C42: =B42*(1+C41) -> 10335.155 | D42: =C42*(1+D41) -> 12402.185 | E42: =D42*(1+E41) -> 14262.513 | F42: =E42*(1+F41) -> 15688.765
A43: Bear FCF Margin Assumption | B43: 0.52 | C43: 0.5 | D43: 0.47 | E43: 0.44 | F43: 0.4
A44: Bear FCF ($M) | B44: =B42*B43 -> 3980.9484 | C44: =C42*C43 -> 5167.5773 | D44: =D42*D43 -> 5829.0271 | E44: =E42*E43 -> 6275.5058 | F44: =F42*F43 -> 6275.5058
A47: SECTION C — DCF VALUATION
A48: Cash + US Treasuries ($M) | B48: 8027
A49: Total Debt ($M) | B49: 0
A50: Diluted Shares Outstanding (M) | B50: 2571
A51: Current Share Price ($) | B51: 141.51
A53: Bull DCF — Assumptions & Output
A54: Discount Rate (WACC) | B54: 0.12
A55: Terminal Growth Rate | B55: 0.04
A56: Terminal FCF Margin | B56: 0.55
A57: PV of FCFs ($M) — Year 1 to 5 | B57: =B32/((1+$B$54)^1) -> 3964.5434 | C57: =C32/((1+$B$54)^2) -> 5858.9311 | D57: =D32/((1+$B$54)^3) -> 8108.3422 | E57: =E32/((1+$B$54)^4) -> 10135.428 | F57: =F32/((1+$B$54)^5) -> 11764.336
A58: Sum of PV FCFs ($M) | B58: =SUM(B57,C57,D57,E57,F57) -> 39831.58
A59: Terminal Year FCF ($M) | B59: =F30*$B$56 -> 18391.982
A60: Terminal Value ($M) [Gordon Growth] | B60: =B59*(1+$B$55)/($B$54-$B$55) -> 239095.76
A61: PV of Terminal Value ($M) | B61: =B60/((1+$B$54)^5) -> 135669.36
A62: Enterprise Value ($M) | B62: =B58+B61 -> 175500.94
A63: Equity Value ($M) [EV + Cash - Debt] | B63: =B62+$B$48-$B$49 -> 183527.94
A64: Intrinsic Value Per Share ($) | B64: =B63/$B$50 -> 71.383872
A65: % Premium(-)/Discount(+) vs Current Price | B65: =($B$51-B64)/B64 -> 0.98238055
A67: Base DCF — Assumptions & Output
A68: Discount Rate (WACC) | B68: 0.13
A69: Terminal Growth Rate | B69: 0.035
A70: Terminal FCF Margin | B70: 0.5
A71: PV of FCFs ($M) — Year 1 to 5 | B71: =B38/((1+$B$68)^1) -> 3793.9604 | C71: =C38/((1+$B$68)^2) -> 5036.2306 | D71: =D38/((1+$B$68)^3) -> 5909.2939 | E71: =E38/((1+$B$68)^4) -> 6417.9781 | F71: =F38/((1+$B$68)^5) -> 6453.7387
A72: Sum of PV FCFs ($M) | B72: =SUM(B71,C71,D71,E71,F71) -> 27611.202
A73: Terminal Year FCF ($M) | B73: =F36*$B$70 -> 11433.265
A74: Terminal Value ($M) [Gordon Growth] | B74: =B73*(1+$B$69)/($B$68-$B$69) -> 124562.41
A75: PV of Terminal Value ($M) | B75: =B74/((1+$B$68)^5) -> 67607.486
A76: Enterprise Value ($M) | B76: =B72+B75 -> 95218.687
A77: Equity Value ($M) [EV + Cash - Debt] | B77: =B76+$B$48-$B$49 -> 103245.69
A78: Intrinsic Value Per Share ($) | B78: =B77/$B$50 -> 40.157794
A79: % Premium(-)/Discount(+) vs Current Price | B79: =($B$51-B78)/B78 -> 2.523849
A81: Bear DCF — Assumptions & Output
A82: Discount Rate (WACC) | B82: 0.15
A83: Terminal Growth Rate | B83: 0.03
A84: Terminal FCF Margin | B84: 0.4
A85: PV of FCFs ($M) — Year 1 to 5 | B85: =B44/((1+$B$82)^1) -> 3461.6943 | C85: =C44/((1+$B$82)^2) -> 3907.4308 | D85: =D44/((1+$B$82)^3) -> 3832.68 | E85: =E44/((1+$B$82)^4) -> 3588.0408 | F85: =F44/((1+$B$82)^5) -> 3120.0355
A86: Sum of PV FCFs ($M) | B86: =SUM(B85,C85,D85,E85,F85) -> 17909.881
A87: Terminal Year FCF ($M) | B87: =F42*$B$84 -> 6275.5058
A88: Terminal Value ($M) [Gordon Growth] | B88: =B87*(1+$B$83)/($B$82-$B$83) -> 53864.758
A89: PV of Terminal Value ($M) | B89: =B88/((1+$B$82)^5) -> 26780.305
A90: Enterprise Value ($M) | B90: =B86+B89 -> 44690.186
A91: Equity Value ($M) [EV + Cash - Debt] | B91: =B90+$B$48-$B$49 -> 52717.186
A92: Intrinsic Value Per Share ($) | B92: =B91/$B$50 -> 20.504545
A93: % Premium(-)/Discount(+) vs Current Price | B93: =($B$51-B92)/B92 -> 5.9013966
A95: SECTION D — RULE OF 40 (HISTORICAL)
A96: Period | B96: Revenue Growth | C96: Adj. Op Margin | D96: Rule of 40 Score
A97: FY2025 | B97: 0.56 | C97: 0.5 | D97: =(B97+C97)*100 -> 106
A98: Q1 2026 | B98: 0.85 | C98: 0.6 | D98: =(B98+C98)*100 -> 145

Sheet NOW_Model
A1: SERVICENOW (NOW) — Investment Analysis Model
A2: SECTION A — HISTORICAL DATA (FY2025–Q1 2026)
A3: Metric | B3: FY2025 | C3: Q1 2026
A4: Subscription Revenue ($M) | B4: 12840 | C4: 3671
A5: Total Revenue ($M) | B5: 13285 | C5: 3770
A6: Sub Revenue YoY Growth | B6: 0.21 | C6: 0.22
A7: GAAP Gross Margin | C7: 0.75
A8: Non-GAAP Gross Margin | C8: 0.795
A9: Sub Gross Margin (GAAP) | C9: 0.775
A10: Sub Gross Margin (Non-GAAP) | C10: 0.815
A11: Non-GAAP Operating Margin | C11: 0.32
A12: Non-GAAP FCF Margin | B12: 0.4 | C12: 0.44
A13: cRPO ($M) | C13: 12640
A14: cRPO YoY Growth | C14: 0.225
A15: Total RPO ($M) | C15: 27700
A16: Total RPO YoY Growth | C16: 0.25
A17: SBC ($M) | C17: 547
A18: SBC % of Revenue | C18: 0.145
A20: SECTION D — KEY SaaS METRICS (Q1 2026)
A21: Metric | B21: Value | C21: Growth / Note
A22: Customers >$5M ACV | B22: 630 | C22: +22% YoY
A23: Transactions >$5M ACV (Q1) | B23: 16 | C23: +80% YoY
A24: Now Assist >$1M ACV Customers | C24: +130% YoY
A27: SECTION B — REVENUE & FCF PROJECTIONS (FY2026–FY2030)
A28: FY2025 Total Revenue ($M) [Base year] | B28: 13285
A29: FY2026 Guided Revenue ($M) [Sub $15,755M + PS ~$345M] | B29: 16100
A30: Year | B30: FY2026 | C30: FY2027 | D30: FY2028 | E30: FY2029 | F30: FY2030
A31: Bull Scenario
A32: Bull Rev Growth Assumption | B32: 0.22 | C32: 0.22 | D32: 0.2 | E32: 0.18 | F32: 0.16
A33: Bull Revenue ($M) | B33: =$B$29 -> 16100 | C33: =B33*(1+C32) -> 19642 | D33: =C33*(1+D32) -> 23570.4 | E33: =D33*(1+E32) -> 27813.072 | F33: =E33*(1+F32) -> 32263.164
A34: Bull FCF Margin Assumption | B34: 0.37 | C34: 0.4 | D34: 0.42 | E34: 0.43 | F34: 0.44
A35: Bull FCF ($M) | B35: =B33*B34 -> 5957 | C35: =C33*C34 -> 7856.8 | D35: =D33*D34 -> 9899.568 | E35: =E33*E34 -> 11959.621 | F35: =F33*F34 -> 14195.792
A37: Base Scenario
A38: Base Rev Growth Assumption | B38: 0.22 | C38: 0.2 | D38: 0.18 | E38: 0.15 | F38: 0.12
A39: Base Revenue ($M) | B39: =$B$29 -> 16100 | C39: =B39*(1+C38) -> 19320 | D39: =C39*(1+D38) -> 22797.6 | E39: =D39*(1+E38) -> 26217.24 | F39: =E39*(1+F38) -> 29363.309
A40: Base FCF Margin Assumption | B40: 0.35 | C40: 0.37 | D40: 0.39 | E40: 0.4 | F40: 0.41
A41: Base FCF ($M) | B41: =B39*B40 -> 5635 | C41: =C39*C40 -> 7148.4 | D41: =D39*D40 -> 8891.064 | E41: =E39*E40 -> 10486.896 | F41: =F39*F40 -> 12038.957
A43: Bear Scenario
A44: Bear Rev Growth Assumption | B44: 0.22 | C44: 0.15 | D44: 0.12 | E44: 0.1 | F44: 0.08
A45: Bear Revenue ($M) | B45: =$B$29 -> 16100 | C45: =B45*(1+C44) -> 18515 | D45: =C45*(1+D44) -> 20736.8 | E45: =D45*(1+E44) -> 22810.48 | F45: =E45*(1+F44) -> 24635.318
A46: Bear FCF Margin Assumption | B46: 0.32 | C46: 0.33 | D46: 0.34 | E46: 0.35 | F46: 0.36
A47: Bear FCF ($M) | B47: =B45*B46 -> 5152 | C47: =C45*C46 -> 6109.95 | D47: =D45*D46 -> 7050.512 | E47: =E45*E46 -> 7983.668 | F47: =F45*F46 -> 8868.7146
A50: SECTION C — DCF VALUATION
A51: Net Cash Position ($M) [Cash+Mkt Securities-Debt] | B51: 3691
A52: Diluted Shares Outstanding (M) | B52: 1040
A53: Current Share Price ($) | B53: 119.29
A55: Bull DCF — Assumptions & Output
A56: Discount Rate (WACC) | B56: 0.1
A57: Terminal Growth Rate | B57: 0.04
A58: Terminal FCF Margin | B58: 0.42
A59: PV of FCFs ($M) — Year 1 to 5 | B59: =B35/((1+$B$56)^1) -> 5415.4545 | C59: =C35/((1+$B$56)^2) -> 6493.2231 | D59: =D35/((1+$B$56)^3) -> 7437.692 | E59: =E35/((1+$B$56)^4) -> 8168.582 | F59: =F35/((1+$B$56)^5) -> 8814.4699
A60: Sum of PV FCFs ($M) | B60: =SUM(B59,C59,D59,E59,F59) -> 36329.422
A61: Terminal Year FCF ($M) | B61: =F33*$B$58 -> 13550.529
A62: Terminal Value ($M) [Gordon Growth] | B62: =B61*(1+$B$57)/($B$56-$B$57) -> 234875.83
A63: PV of Terminal Value ($M) | B63: =B62/((1+$B$56)^5) -> 145839.41
A64: Enterprise Value ($M) | B64: =B60+B63 -> 182168.83
A65: Equity Value ($M) [EV + Net Cash] | B65: =B64+$B$51 -> 185859.83
A66: Intrinsic Value Per Share ($) | B66: =B65/$B$52 -> 178.71138
A67: % Premium(-)/Discount(+) vs Current Price | B67: =($B$53-B66)/B66 -> -0.33249913
A69: Base DCF — Assumptions & Output
A70: Discount Rate (WACC) | B70: 0.11
A71: Terminal Growth Rate | B71: 0.035
A72: Terminal FCF Margin | B72: 0.4
A73: PV of FCFs ($M) — Year 1 to 5 | B73: =B41/((1+$B$70)^1) -> 5076.5766 | C73: =C41/((1+$B$70)^2) -> 5801.8018 | D73: =D41/((1+$B$70)^3) -> 6501.0694 | E73: =E41/((1+$B$70)^4) -> 6908.0432 | F73: =F41/((1+$B$70)^5) -> 7144.5348
A74: Sum of PV FCFs ($M) | B74: =SUM(B73,C73,D73,E73,F73) -> 31432.026
A75: Terminal Year FCF ($M) | B75: =F39*$B$72 -> 11745.324
A76: Terminal Value ($M) [Gordon Growth] | B76: =B75*(1+$B$71)/($B$70-$B$71) -> 162085.46
A77: PV of Terminal Value ($M) | B77: =B76/((1+$B$70)^5) -> 96189.834
A78: Enterprise Value ($M) | B78: =B74+B77 -> 127621.86
A79: Equity Value ($M) [EV + Net Cash] | B79: =B78+$B$51 -> 131312.86
A80: Intrinsic Value Per Share ($) | B80: =B79/$B$52 -> 126.26237
A81: % Premium(-)/Discount(+) vs Current Price | B81: =($B$53-B80)/B80 -> -0.055221248
A83: Bear DCF — Assumptions & Output
A84: Discount Rate (WACC) | B84: 0.12
A85: Terminal Growth Rate | B85: 0.03
A86: Terminal FCF Margin | B86: 0.35
A87: PV of FCFs ($M) — Year 1 to 5 | B87: =B47/((1+$B$84)^1) -> 4600 | C87: =C47/((1+$B$84)^2) -> 4870.8147 | D87: =D47/((1+$B$84)^3) -> 5018.4152 | E87: =E47/((1+$B$84)^4) -> 5073.7653 | F87: =F47/((1+$B$84)^5) -> 5032.3469
A88: Sum of PV FCFs ($M) | B88: =SUM(B87,C87,D87,E87,F87) -> 24595.342
A89: Terminal Year FCF ($M) | B89: =F45*$B$86 -> 8622.3614
A90: Terminal Value ($M) [Gordon Growth] | B90: =B89*(1+$B$85)/($B$84-$B$85) -> 98678.136
A91: PV of Terminal Value ($M) | B91: =B90/((1+$B$84)^5) -> 55992.625
A92: Enterprise Value ($M) | B92: =B88+B91 -> 80587.967
A93: Equity Value ($M) [EV + Net Cash] | B93: =B92+$B$51 -> 84278.967
A94: Intrinsic Value Per Share ($) | B94: =B93/$B$52 -> 81.037468
A95: % Premium(-)/Discount(+) vs Current Price | B95: =($B$53-B94)/B94 -> 0.47203513

Sheet Comparison
A1: PLTR vs NOW — Comparative Analysis
A3: RULE OF 40 COMPARISON (Q1 2026)
A4: Company | B4: Revenue Growth | C4: FCF/Op Margin | D4: Rule of 40 | E4: Forward EV/S | F4: EV/FCF | G4: Notes
A5: PLTR (Q1 2026) | B5: 0.85 | C5: 0.6 | D5: =(B5+C5)*100 -> 145 | E5: 46.5 | F5: 82.7 | G5: Adj. op margin; AI infrastructure
A6: NOW (Q1 2026) | B6: 0.22 | C6: 0.32 | D6: =(B6+C6)*100 -> 54 | E6: 7.5 | F6: 21.3 | G6: Non-GAAP op margin; Enterprise workflow
A9: PEER COMPARABLES TABLE (Approximate, June 2026 — VERIFY BEFORE USE)
A10: Company | B10: Ticker | C10: Fwd Rev Growth | D10: FCF Margin | E10: Rule of 40 | F10: Fwd EV/S | G10: Segment / Comment
A11: Palantir | B11: PLTR | C11: 0.71 | D11: 0.56 | E11: =(C11+D11)*100 -> 127 | F11: 46.5 | G11: AI infrastructure / data analytics
A12: ServiceNow | B12: NOW | C12: 0.22 | D12: 0.35 | E12: =(C12+D12)*100 -> 57 | F12: 7.5 | G12: Enterprise workflow / AI platform
A13: Salesforce | B13: CRM | C13: 0.09 | D13: 0.32 | E13: =(C13+D13)*100 -> 41 | F13: 6.5 | G13: CRM / cloud applications
A14: Snowflake | B14: SNOW | C14: 0.23 | D14: 0.18 | E14: =(C14+D14)*100 -> 41 | F14: 10 | G14: Data cloud / analytics platform
A15: Datadog | B15: DDOG | C15: 0.23 | D15: 0.25 | E15: =(C15+D15)*100 -> 48 | F15: 14 | G15: Observability / monitoring
A16: CrowdStrike | B16: CRWD | C16: 0.2 | D16: 0.28 | E16: =(C16+D16)*100 -> 48 | F16: 20 | G16: Cybersecurity / endpoint protection
A17: Workday | B17: WDAY | C17: 0.14 | D17: 0.25 | E17: =(C17+D17)*100 -> 39 | F17: 6 | G17: HCM / Finance cloud
A19: NOTE: Peer comps are approximate estimates as of June 2026. Verify against current Bloomberg/FactSet before use.
A21: VALUATION SUMMARY — CURRENT PRICE vs DCF INTRINSIC VALUE
A22: Company | B22: Current Price | C22: DCF Bull | D22: DCF Base | E22: DCF Bear | F22: vs Bull (%) | G22: vs Base (%)
A23: PLTR | B23: =PLTR_Model!$B$51 -> 141.51 | C23: =PLTR_Model!$B$64 -> 71.383872 | D23: =PLTR_Model!$B$78 -> 40.157794 | E23: =PLTR_Model!$B$92 -> 20.504545 | F23: =(B23-C23)/C23 -> 0.98238055 | G23: =(B23-D23)/D23 -> 2.523849
A24: NOW | B24: =NOW_Model!$B$53 -> 119.29 | C24: =NOW_Model!$B$66 -> 178.71138 | D24: =NOW_Model!$B$80 -> 126.26237 | E24: =NOW_Model!$B$94 -> 81.037468 | F24: =(B24-C24)/C24 -> -0.33249913 | G24: =(B24-D24)/D24 -> -0.055221248

Sheet Options_Strategy
A1: OPTIONS STRATEGY — PLTR & NOW (June 2026)
A3: MARKET DATA REFERENCE (June 2026)
A4: Ticker | B4: Price | C4: IV (%) | D4: IV Rank | E4: 200-day SMA | F4: 52-wk Low | G4: 52-wk High | H4: RSI (est.) | I4: Notes
A5: PLTR | B5: 141.51 | C5: 0.6879 | D5: 46.73 | E5: 162 | I5: IV 68.79%; IVR 46.73; trades ~12% below 200-day SMA of $162
A6: NOW | B6: 119.29 | F6: 81.24 | G6: 211.48 | I6: 52-wk range $81.24-$211.48; near lower historical range
A9: OPTIONS STRATEGIES SUMMARY TABLE
A10: Strategy | B10: Ticker | C10: Structure | D10: Strike(s) | E10: Expiry | F10: Premium (est.) | G10: Max Gain | H10: Max Loss | I10: Rationale
A11: 1 — Bear Call Spread | B11: PLTR | C11: Sell $155 Call / Buy $165 Call | D11: $155 / $165 | E11: Aug 2026 (~2mo) | F11: ~$3-4 credit | G11: ~$3-4 credit | H11: ~$6-7 per spread | I11: PLTR trades far above DCF intrinsic; moderate IVR 46.73 supports premium selling; protects existing holders from stall scenarios
A12: 2 — Covered Call | B12: PLTR | C12: Sell OTM Call vs long shares | D12: $155-160 | E12: 6-8 weeks out | F12: ~$5-7/contract | G12: ~$5-7 premium | H12: Uncapped above strike | I12: At ~69% IV, significant premium income; reduces cost basis; best for long holders not expecting near-term rally
A13: 3 — Cash-Secured Put | B13: PLTR | C13: Sell OTM Put / Hold cash | D13: $120-125 | E13: ~8 weeks out | F13: ~$8-10 | G13: ~$8-10 premium | H13: Assigned at ~$110-117 | I13: Effective cost basis ~$110-117 if assigned (near DCF bull ~$78 zone); income if PLTR holds above strike
A14: 1 — Long Call Spread | B14: NOW | C14: Buy $120 Call / Sell $150 Call | D14: $120 / $150 | E14: Jan 2027 (~7mo) | F14: ~$10-12 debit | G14: ~$18-20 at $150 | H14: ~$10-12 debit | I14: Defined risk bullish play; NOW at/below DCF base case; captures recovery toward $129+ intrinsic value; ~1.7:1 R/R
A15: 2 — Cash-Secured Put | B15: NOW | C15: Sell OTM Put / Hold cash | D15: $110 | E15: 8-10 weeks out | F15: ~$7-9 | G15: ~$7-9 premium | H15: Assigned at ~$101-103 | I15: Entry well below DCF base $129; significant margin of safety if assigned; income generation otherwise
A16: 3 — Covered Call Enh. | B16: NOW | C16: Sell OTM Call vs long shares | D16: $135-140 | E16: 6-8 weeks out | F16: ~$4-6/contract | G16: ~$4-6 premium | H16: Uncapped above strike | I16: Income enhancement for existing NOW holders; generates yield while holding quality name near lows
A19: DISCLAIMER: Options strategies are for educational/analytical purposes only. Verify all premiums with live market data. Options trading involves significant risk of loss. Consult a licensed financial advisor before trading.
